gparams/__about__.py
gparams/__init__.py
gparams/ini2yml.py
gparams/parameters.py
gparams/yml2ini.py
gparams/scripts/__init__.py
gparams/scripts/main.py
gparams-1.0.2.dist-info/LICENSE.txt
gparams-1.0.2.dist-info/METADATA
gparams-1.0.2.dist-info/RECORD
gparams-1.0.2.dist-info/WHEEL
gparams-1.0.2.dist-info/entry_points.txt
gparams-1.0.2.dist-info/top_level.txt
