Metadata-Version: 2.1
Name: gparams
Version: 1.0.2
Summary: A kit to process the parameters of the GeneDock workflow (help for batch delivery).
Home-page: https://www.genedock.com
Author: Rao Mengnan
Author-email: raomengnan@genedock.com
Maintainer: GeneDock Contributor
Maintainer-email: raomengnan@genedock.com
License: UNKNOWN
Platform: Independent
Classifier: Environment :: Console
Classifier: License :: OSI Approved :: Apache Software License
Classifier: Intended Audience :: Customer Service
Classifier: Intended Audience :: End Users/Desktop
Classifier: Operating System :: OS Independent
Classifier: Programming Language :: Python
Requires-Dist: PyYAML (==3.13)
Requires-Dist: Jinja2 (==2.10)
